natural_shell/__init__.py
natural_shell/cli.py
natural_shell/command_executor.py
natural_shell/language_model.py
natural_shell/parser.py
natural_shell-0.1.0.dist-info/LICENSE
natural_shell-0.1.0.dist-info/METADATA
natural_shell-0.1.0.dist-info/WHEEL
natural_shell-0.1.0.dist-info/entry_points.txt
natural_shell-0.1.0.dist-info/top_level.txt
natural_shell-0.1.0.dist-info/RECORD
