Metadata-Version: 2.1
Name: natural-shell
Version: 0.1.0
Summary: A tool for converting natural language to shell commands
Home-page: https://github.com/theghostrat/NaturalShell
Author: Sourabh Singh
Classifier: Programming Language :: Python :: 3
Classifier: License :: OSI Approved :: MIT License
Classifier: Operating System :: OS Independent
Requires-Python: >=3.7
License-File: LICENSE
Requires-Dist: langchain
Requires-Dist: langchain-google-genai
Requires-Dist: langchain-openai
Requires-Dist: langchain-anthropic
Requires-Dist: pyyaml
